<ToolBar>
	<Group width="69%">
		<Tool symbol="icon-sidebar" click="toggle-sidebar" state="active"/>

		<Tool symbol="icon-send-receive"/>
		<Tool symbol="icon-new-mail" click="new-mail"/>

		<Options>
			<Tool symbol="icon-trash" state="disabled"/>
			<Tool symbol="icon-archive" state="disabled"/>
		</Options>
		
		<Tool symbol="icon-junk" state="disabled"/>

		<Options>
			<Tool symbol="icon-reply" state="disabled"/>
			<Tool symbol="icon-reply-all" state="disabled"/>
			<Tool symbol="icon-forward" state="disabled"/>
		</Options>

		<Tool symbol="icon-flag" menu="toolbar-flags" state="disabled"/>

	</Group>
	<Group width="31%">
		<Search placeholder="Search"/>
	</Group>
</ToolBar>